udata_metrics/__init__.py
udata_metrics/metrics.py
udata_metrics/settings.py
udata_metrics/tasks.py
udata_metrics/views.py
udata_metrics/templates/dataset-metrics.html
udata_metrics/templates/organization-metrics.html
udata_metrics/templates/reuse-metrics.html
udata_metrics/templates/site-metrics.html
udata_metrics/templates/macros/metrics.html
udata_metrics/translations/udata_metrics.pot
udata_metrics/translations/fr/LC_MESSAGES/udata_metrics.mo
udata_metrics/translations/fr/LC_MESSAGES/udata_metrics.po
udata_metrics-2.0.4.dist-info/METADATA
udata_metrics-2.0.4.dist-info/WHEEL
udata_metrics-2.0.4.dist-info/entry_points.txt
udata_metrics-2.0.4.dist-info/top_level.txt
udata_metrics-2.0.4.dist-info/RECORD
