Metadata-Version: 2.1
Name: udata-metrics
Version: 2.0.4
Summary: Connexion handler to metrics service for udata
Home-page: https://github.com/opendatateam/udata-metrics
Author: Open Data Team
Author-email: contact@opendata.team
License: AGPL
Keywords: udata metrics
Classifier: Development Status :: 3 - Alpha
Classifier: Programming Language :: Python
Classifier: Environment :: Web Environment
Classifier: Operating System :: OS Independent
Classifier: Intended Audience :: Developers
Classifier: Topic :: System :: Software Distribution
Classifier: Programming Language :: Python
Classifier: Programming Language :: Python :: 2
Classifier: Programming Language :: Python :: 2.7
Classifier: Topic :: Software Development :: Libraries :: Python Modules
Requires-Python: >=3.7
Requires-Dist: udata >=8.0.1
Requires-Dist: udata-front >=4.0.0
Provides-Extra: test
Requires-Dist: httpretty ==1.1.4 ; extra == 'test'
Requires-Dist: mock ==5.0.1 ; extra == 'test'
Requires-Dist: pytest-flask ==1.2.0 ; extra == 'test'
Requires-Dist: pytest-sugar ==0.9.6 ; extra == 'test'
Requires-Dist: pytest ==7.2.1 ; extra == 'test'
Requires-Dist: requests-mock ==1.10.0 ; extra == 'test'
